bauhaus/__init__.py
bauhaus/constraint_builder.py
bauhaus/core.py
bauhaus/utils.py
bauhaus-1.2.0.dist-info/LICENSE
bauhaus-1.2.0.dist-info/METADATA
bauhaus-1.2.0.dist-info/WHEEL
bauhaus-1.2.0.dist-info/top_level.txt
bauhaus-1.2.0.dist-info/RECORD
