Metadata-Version: 2.1
Name: bauhaus
Version: 1.2.0
Summary: Build logical theories for SAT solvers on the fly
Author: Karishma Daga, Christian Muise
Author-email: karishma.daga@queensu.ca, christian.muise@queensu.ca
License: MIT
Project-URL: Documentation, https://bauhaus.readthedocs.io/
Project-URL: Source, https://github.com/QuMuLab/bauhaus
Keywords: logic nnf sat constraints encodings
Classifier: Intended Audience :: Science/Research
Classifier: Topic :: Scientific/Engineering
Classifier: Topic :: Scientific/Engineering :: Mathematics
Classifier: Development Status :: 4 - Beta
Classifier: Programming Language :: Python
Classifier: Programming Language :: Python :: 3
Classifier: Programming Language :: Python :: 3.4
Classifier: Programming Language :: Python :: 3.5
Classifier: Programming Language :: Python :: 3.6
Classifier: Programming Language :: Python :: 3.7
Classifier: Programming Language :: Python :: 3.8
Classifier: Programming Language :: Python :: 3 :: Only
Requires-Python: >=3.4
License-File: LICENSE
Requires-Dist: nnf>=0.1.0
Provides-Extra: pysat
Requires-Dist: python-sat>=0.1; extra == "pysat"
